pyatlassian/__init__.py
pyatlassian/_version.py
pyatlassian/api.py
pyatlassian/pagi.py
pyatlassian/paths.py
pyatlassian/atlassian/__init__.py
pyatlassian/atlassian/_version.py
pyatlassian/atlassian/api.py
pyatlassian/atlassian/arg.py
pyatlassian/atlassian/exc.py
pyatlassian/atlassian/model.py
pyatlassian/atlassian_confluence/__init__.py
pyatlassian/atlassian_confluence/_version.py
pyatlassian/atlassian_confluence/api.py
pyatlassian/atlassian_confluence/children.py
pyatlassian/atlassian_confluence/label.py
pyatlassian/atlassian_confluence/model.py
pyatlassian/atlassian_confluence/page.py
pyatlassian/atlassian_confluence/space.py
pyatlassian/atlassian_confluence/typehint.py
pyatlassian/atlassian_confluence/utils.py
pyatlassian/atlassian_jira/__init__.py
pyatlassian/atlassian_jira/api.py
pyatlassian/atlassian_jira/issue_search.py
pyatlassian/atlassian_jira/issues.py
pyatlassian/atlassian_jira/model.py
pyatlassian/atlassian_jira/projects.py
pyatlassian/atlassian_jira/typehint.py
pyatlassian/atlassian_jira/users.py
pyatlassian/atlassian_jira/utils.py
pyatlassian/docs/__init__.py
pyatlassian/tests/__init__.py
pyatlassian/tests/api_keys.py
pyatlassian/tests/helper.py
pyatlassian/tests/helper_confluence.py
pyatlassian/vendor/__init__.py
pyatlassian/vendor/pytest_cov_helper.py
pyatlassian-0.3.2.dist-info/licenses/AUTHORS.rst
pyatlassian-0.3.2.dist-info/licenses/LICENSE.txt
pyatlassian-0.3.2.dist-info/METADATA
pyatlassian-0.3.2.dist-info/WHEEL
pyatlassian-0.3.2.dist-info/top_level.txt
pyatlassian-0.3.2.dist-info/RECORD
